main.py
setup.py
open_clips_torch.egg-info/PKG-INFO
open_clips_torch.egg-info/SOURCES.txt
open_clips_torch.egg-info/dependency_links.txt
open_clips_torch.egg-info/requires.txt
open_clips_torch.egg-info/top_level.txt